vpn_monitor/__init__.py
vpn_monitor/gui.py
vpn_monitor/main.py
vpn_monitor/monitor.py
vpn_monitor/tray.py
vpn_monitor-1.1.0.dist-info/licenses/LICENSE
vpn_monitor-1.1.0.dist-info/METADATA
vpn_monitor-1.1.0.dist-info/WHEEL
vpn_monitor-1.1.0.dist-info/entry_points.txt
vpn_monitor-1.1.0.dist-info/top_level.txt
vpn_monitor-1.1.0.dist-info/RECORD
