Metadata-Version: 2.4
Name: vpn-monitor
Version: 1.1.0
Summary: Monitors Windows App and enforces VPN usage.
Author: VPN Monitor Contributors
License: MIT
Project-URL: Homepage, https://github.com/henrykp/vpn_status_monitor
Project-URL: Repository, https://github.com/henrykp/vpn_status_monitor
Project-URL: Issues, https://github.com/henrykp/vpn_status_monitor/issues
Keywords: vpn,monitor,windows,security,network
Classifier: Development Status :: 4 - Beta
Classifier: Environment :: Win32 (MS Windows)
Classifier: Intended Audience :: End Users/Desktop
Classifier: License :: OSI Approved :: MIT License
Classifier: Operating System :: Microsoft :: Windows
Classifier: Programming Language :: Python :: 3
Classifier: Programming Language :: Python :: 3.8
Classifier: Programming Language :: Python :: 3.9
Classifier: Programming Language :: Python :: 3.10
Classifier: Programming Language :: Python :: 3.11
Classifier: Programming Language :: Python :: 3.12
Classifier: Topic :: Security
Classifier: Topic :: System :: Networking :: Monitoring
Requires-Python: >=3.8
License-File: LICENSE
Requires-Dist: psutil
Requires-Dist: requests
Requires-Dist: pystray
Requires-Dist: Pillow
Dynamic: license-file
